{
  "versions": [
    {
      "version": 1,
      "timestamp": "2025-09-11T22:10:00.670087",
      "file_hashes": {
        "learning_history.json": "679872181af7badac06a9a5916349d68",
        "core.json": "1ed798cc82d0474c6f251754cefb69da",
        "architecture.json": "f7c642e748a3b95b4a1835549dac9513",
        "user_experience.json": "d6d9d73512dd9e8f290966fdd6af2f4c",
        "troubleshooting.json": "f60784447de0dd862fa6ebed3d4ea091"
      },
      "project": "AI Context Manager",
      "changes": "Self-maintenance: Context files updated",
      "meta_note": "AI Context Manager maintaining its own context"
    },
    {
      "version": 2,
      "timestamp": "2025-09-11T22:10:50.387602",
      "file_hashes": {
        "learning_history.json": "85f933c77a9b996f19326852cca7167e",
        "core.json": "3644e389eed9208241ac239e97895426",
        "architecture.json": "f455143563ef6b392e0f333cc4d6286e",
        "user_experience.json": "eb0bbbe253726fe5ee005d3115875c1e",
        "maintenance_log.json": "66c0dc923d958f248f5e7307d9f15bc8",
        "troubleshooting.json": "2bc627986f1500ab1ff809aebd32fa7d"
      },
      "project": "AI Context Manager",
      "changes": "Self-maintenance: Context files updated",
      "meta_note": "AI Context Manager maintaining its own context"
    },
    {
      "version": 3,
      "timestamp": "2025-09-11T22:23:19.013368",
      "file_hashes": {
        "learning_history.json": "679872181af7badac06a9a5916349d68",
        "core.json": "1ed798cc82d0474c6f251754cefb69da",
        "architecture.json": "f7c642e748a3b95b4a1835549dac9513",
        "user_experience.json": "d6d9d73512dd9e8f290966fdd6af2f4c",
        "maintenance_log.json": "36f526fe6c72fc84adc0b2139b4590b0",
        "troubleshooting.json": "f60784447de0dd862fa6ebed3d4ea091"
      },
      "project": "AI Context Manager",
      "changes": "Self-maintenance: Context files updated",
      "meta_note": "AI Context Manager maintaining its own context"
    }
  ],
  "current_version": 3
}
